{
  "lastUpdated": "2026-03-31T11:50:59.324Z",
  "entries": [
    {
      "url": "https://www.brex.com/careers/8457349002?gh_jid=8457349002",
      "ts": 1773758526385
    },
    {
      "url": "https://www.brex.com/careers/8409267002?gh_jid=8409267002",
      "ts": 1773758526385
    },
    {
      "url": "https://www.veriff.com/careers/position/8436756002?gh_jid=8436756002",
      "ts": 1774007887852
    },
    {
      "url": "https://www.brex.com/careers/8409265002?gh_jid=8409265002",
      "ts": 1774007887852
    },
    {
      "url": "https://www.brex.com/careers/8408803002?gh_jid=8408803002",
      "ts": 1774093643993
    },
    {
      "url": "https://www.brex.com/careers/8409273002?gh_jid=8409273002",
      "ts": 1774536778636
    },
    {
      "url": "https://www.brex.com/careers/8457370002?gh_jid=8457370002",
      "ts": 1774957859324
    },
    {
      "url": "https://www.salesloft.com/company/careers?gh_jid=7697870",
      "ts": 1774957859324
    }
  ]
}